{
    "album_type": "single",
    "artists": [
        {
            "external_urls": {
                "spotify": "https://open.spotify.com/artist/4FqPRilb0Ja0TKG3RS3y4s"
            },
            "href": "https://api.spotify.com/v1/artists/4FqPRilb0Ja0TKG3RS3y4s",
            "id": "4FqPRilb0Ja0TKG3RS3y4s",
            "name": "Steve Angello",
            "type": "artist",
            "uri": "spotify:artist:4FqPRilb0Ja0TKG3RS3y4s"
        },
        {
            "external_urls": {
                "spotify": "https://open.spotify.com/artist/132Hhe61bhvXtkygENHZHA"
            },
            "href": "https://api.spotify.com/v1/artists/132Hhe61bhvXtkygENHZHA",
            "id": "132Hhe61bhvXtkygENHZHA",
            "name": "Wh0",
            "type": "artist",
            "uri": "spotify:artist:132Hhe61bhvXtkygENHZHA"
        }
    ],
    "copyrights": [
        {
            "text": "\u00a9 2023 Size Records UK Ltd, under exclusive license to UMG Recordings, Inc.",
            "type": "C"
        },
        {
            "text": "\u2117 2023 Size Records UK Ltd, under exclusive license to UMG Recordings, Inc.",
            "type": "P"
        }
    ],
    "external_ids": {
        "upc": "00602458269178"
    },
    "external_urls": {
        "spotify": "https://open.spotify.com/album/36WVqPt4HocsuiPQer82ob"
    },
    "genres": [],
    "href": "https://api.spotify.com/v1/albums/36WVqPt4HocsuiPQer82ob",
    "id": "36WVqPt4HocsuiPQer82ob",
    "images": [
        {
            "height": 640,
            "url": "https://i.scdn.co/image/ab67616d0000b273d1b85127f6d81eb690a68022",
            "width": 640
        },
        {
            "height": 300,
            "url": "https://i.scdn.co/image/ab67616d00001e02d1b85127f6d81eb690a68022",
            "width": 300
        },
        {
            "height": 64,
            "url": "https://i.scdn.co/image/ab67616d00004851d1b85127f6d81eb690a68022",
            "width": 64
        }
    ],
    "is_playable": true,
    "label": "Astralwerks",
    "name": "What You Need",
    "popularity": 46,
    "release_date": "2023-07-21",
    "release_date_precision": "day",
    "total_tracks": 1,
    "tracks": {
        "href": "https://api.spotify.com/v1/albums/36WVqPt4HocsuiPQer82ob/tracks?offset=0&limit=50&market=KR",
        "items": [
            {
                "artists": [
                    {
                        "external_urls": {
                            "spotify": "https://open.spotify.com/artist/4FqPRilb0Ja0TKG3RS3y4s"
                        },
                        "href": "https://api.spotify.com/v1/artists/4FqPRilb0Ja0TKG3RS3y4s",
                        "id": "4FqPRilb0Ja0TKG3RS3y4s",
                        "name": "Steve Angello",
                        "type": "artist",
                        "uri": "spotify:artist:4FqPRilb0Ja0TKG3RS3y4s"
                    },
                    {
                        "external_urls": {
                            "spotify": "https://open.spotify.com/artist/132Hhe61bhvXtkygENHZHA"
                        },
                        "href": "https://api.spotify.com/v1/artists/132Hhe61bhvXtkygENHZHA",
                        "id": "132Hhe61bhvXtkygENHZHA",
                        "name": "Wh0",
                        "type": "artist",
                        "uri": "spotify:artist:132Hhe61bhvXtkygENHZHA"
                    }
                ],
                "disc_number": 1,
                "duration_ms": 218040,
                "explicit": false,
                "external_urls": {
                    "spotify": "https://open.spotify.com/track/2KR32tVW39lfG4tO1yOwdq"
                },
                "href": "https://api.spotify.com/v1/tracks/2KR32tVW39lfG4tO1yOwdq",
                "id": "2KR32tVW39lfG4tO1yOwdq",
                "is_local": false,
                "is_playable": true,
                "name": "What You Need",
                "preview_url": null,
                "track_number": 1,
                "type": "track",
                "uri": "spotify:track:2KR32tVW39lfG4tO1yOwdq"
            }
        ],
        "limit": 50,
        "next": null,
        "offset": 0,
        "previous": null,
        "total": 1
    },
    "type": "album",
    "uri": "spotify:album:36WVqPt4HocsuiPQer82ob"
}{
    "album_type": "single",
    "artists": [
        {
            "external_urls": {
                "spotify": "https://open.spotify.com/artist/4FqPRilb0Ja0TKG3RS3y4s"
            },
            "href": "https://api.spotify.com/v1/artists/4FqPRilb0Ja0TKG3RS3y4s",
            "id": "4FqPRilb0Ja0TKG3RS3y4s",
            "name": "Steve Angello",
            "type": "artist",
            "uri": "spotify:artist:4FqPRilb0Ja0TKG3RS3y4s"
        },
        {
            "external_urls": {
                "spotify": "https://open.spotify.com/artist/132Hhe61bhvXtkygENHZHA"
            },
            "href": "https://api.spotify.com/v1/artists/132Hhe61bhvXtkygENHZHA",
            "id": "132Hhe61bhvXtkygENHZHA",
            "name": "Wh0",
            "type": "artist",
            "uri": "spotify:artist:132Hhe61bhvXtkygENHZHA"
        }
    ],
    "copyrights": [
        {
            "text": "\u00a9 2023 Size Records UK Ltd, under exclusive license to UMG Recordings, Inc.",
            "type": "C"
        },
        {
            "text": "\u2117 2023 Size Records UK Ltd, under exclusive license to UMG Recordings, Inc.",
            "type": "P"
        }
    ],
    "external_ids": {
        "upc": "00602458269178"
    },
    "external_urls": {
        "spotify": "https://open.spotify.com/album/36WVqPt4HocsuiPQer82ob"
    },
    "genres": [],
    "href": "https://api.spotify.com/v1/albums/36WVqPt4HocsuiPQer82ob",
    "id": "36WVqPt4HocsuiPQer82ob",
    "images": [
        {
            "height": 640,
            "url": "https://i.scdn.co/image/ab67616d0000b273d1b85127f6d81eb690a68022",
            "width": 640
        },
        {
            "height": 300,
            "url": "https://i.scdn.co/image/ab67616d00001e02d1b85127f6d81eb690a68022",
            "width": 300
        },
        {
            "height": 64,
            "url": "https://i.scdn.co/image/ab67616d00004851d1b85127f6d81eb690a68022",
            "width": 64
        }
    ],
    "is_playable": true,
    "label": "Astralwerks",
    "name": "What You Need",
    "popularity": 46,
    "release_date": "2023-07-21",
    "release_date_precision": "day",
    "total_tracks": 1,
    "tracks": {
        "href": "https://api.spotify.com/v1/albums/36WVqPt4HocsuiPQer82ob/tracks?offset=0&limit=50&market=KR",
        "items": [
            {
                "artists": [
                    {
                        "external_urls": {
                            "spotify": "https://open.spotify.com/artist/4FqPRilb0Ja0TKG3RS3y4s"
                        },
                        "href": "https://api.spotify.com/v1/artists/4FqPRilb0Ja0TKG3RS3y4s",
                        "id": "4FqPRilb0Ja0TKG3RS3y4s",
                        "name": "Steve Angello",
                        "type": "artist",
                        "uri": "spotify:artist:4FqPRilb0Ja0TKG3RS3y4s"
                    },
                    {
                        "external_urls": {
                            "spotify": "https://open.spotify.com/artist/132Hhe61bhvXtkygENHZHA"
                        },
                        "href": "https://api.spotify.com/v1/artists/132Hhe61bhvXtkygENHZHA",
                        "id": "132Hhe61bhvXtkygENHZHA",
                        "name": "Wh0",
                        "type": "artist",
                        "uri": "spotify:artist:132Hhe61bhvXtkygENHZHA"
                    }
                ],
                "disc_number": 1,
                "duration_ms": 218040,
                "explicit": false,
                "external_urls": {
                    "spotify": "https://open.spotify.com/track/2KR32tVW39lfG4tO1yOwdq"
                },
                "href": "https://api.spotify.com/v1/tracks/2KR32tVW39lfG4tO1yOwdq",
                "id": "2KR32tVW39lfG4tO1yOwdq",
                "is_local": false,
                "is_playable": true,
                "name": "What You Need",
                "preview_url": null,
                "track_number": 1,
                "type": "track",
                "uri": "spotify:track:2KR32tVW39lfG4tO1yOwdq"
            }
        ],
        "limit": 50,
        "next": null,
        "offset": 0,
        "previous": null,
        "total": 1
    },
    "type": "album",
    "uri": "spotify:album:36WVqPt4HocsuiPQer82ob"
}{
    "album_type": "single",
    "artists": [
        {
            "external_urls": {
                "spotify": "https://open.spotify.com/artist/4FqPRilb0Ja0TKG3RS3y4s"
            },
            "href": "https://api.spotify.com/v1/artists/4FqPRilb0Ja0TKG3RS3y4s",
            "id": "4FqPRilb0Ja0TKG3RS3y4s",
            "name": "Steve Angello",
            "type": "artist",
            "uri": "spotify:artist:4FqPRilb0Ja0TKG3RS3y4s"
        },
        {
            "external_urls": {
                "spotify": "https://open.spotify.com/artist/132Hhe61bhvXtkygENHZHA"
            },
            "href": "https://api.spotify.com/v1/artists/132Hhe61bhvXtkygENHZHA",
            "id": "132Hhe61bhvXtkygENHZHA",
            "name": "Wh0",
            "type": "artist",
            "uri": "spotify:artist:132Hhe61bhvXtkygENHZHA"
        }
    ],
    "copyrights": [
        {
            "text": "\u00a9 2023 Size Records UK Ltd, under exclusive license to UMG Recordings, Inc.",
            "type": "C"
        },
        {
            "text": "\u2117 2023 Size Records UK Ltd, under exclusive license to UMG Recordings, Inc.",
            "type": "P"
        }
    ],
    "external_ids": {
        "upc": "00602458269178"
    },
    "external_urls": {
        "spotify": "https://open.spotify.com/album/36WVqPt4HocsuiPQer82ob"
    },
    "genres": [],
    "href": "https://api.spotify.com/v1/albums/36WVqPt4HocsuiPQer82ob",
    "id": "36WVqPt4HocsuiPQer82ob",
    "images": [
        {
            "height": 640,
            "url": "https://i.scdn.co/image/ab67616d0000b273d1b85127f6d81eb690a68022",
            "width": 640
        },
        {
            "height": 300,
            "url": "https://i.scdn.co/image/ab67616d00001e02d1b85127f6d81eb690a68022",
            "width": 300
        },
        {
            "height": 64,
            "url": "https://i.scdn.co/image/ab67616d00004851d1b85127f6d81eb690a68022",
            "width": 64
        }
    ],
    "is_playable": true,
    "label": "Astralwerks",
    "name": "What You Need",
    "popularity": 46,
    "release_date": "2023-07-21",
    "release_date_precision": "day",
    "total_tracks": 1,
    "tracks": {
        "href": "https://api.spotify.com/v1/albums/36WVqPt4HocsuiPQer82ob/tracks?offset=0&limit=50&market=KR",
        "items": [
            {
                "artists": [
                    {
                        "external_urls": {
                            "spotify": "https://open.spotify.com/artist/4FqPRilb0Ja0TKG3RS3y4s"
                        },
                        "href": "https://api.spotify.com/v1/artists/4FqPRilb0Ja0TKG3RS3y4s",
                        "id": "4FqPRilb0Ja0TKG3RS3y4s",
                        "name": "Steve Angello",
                        "type": "artist",
                        "uri": "spotify:artist:4FqPRilb0Ja0TKG3RS3y4s"
                    },
                    {
                        "external_urls": {
                            "spotify": "https://open.spotify.com/artist/132Hhe61bhvXtkygENHZHA"
                        },
                        "href": "https://api.spotify.com/v1/artists/132Hhe61bhvXtkygENHZHA",
                        "id": "132Hhe61bhvXtkygENHZHA",
                        "name": "Wh0",
                        "type": "artist",
                        "uri": "spotify:artist:132Hhe61bhvXtkygENHZHA"
                    }
                ],
                "disc_number": 1,
                "duration_ms": 218040,
                "explicit": false,
                "external_urls": {
                    "spotify": "https://open.spotify.com/track/2KR32tVW39lfG4tO1yOwdq"
                },
                "href": "https://api.spotify.com/v1/tracks/2KR32tVW39lfG4tO1yOwdq",
                "id": "2KR32tVW39lfG4tO1yOwdq",
                "is_local": false,
                "is_playable": true,
                "name": "What You Need",
                "preview_url": null,
                "track_number": 1,
                "type": "track",
                "uri": "spotify:track:2KR32tVW39lfG4tO1yOwdq"
            }
        ],
        "limit": 50,
        "next": null,
        "offset": 0,
        "previous": null,
        "total": 1
    },
    "type": "album",
    "uri": "spotify:album:36WVqPt4HocsuiPQer82ob"
}{
    "album_type": "single",
    "artists": [
        {
            "external_urls": {
                "spotify": "https://open.spotify.com/artist/4FqPRilb0Ja0TKG3RS3y4s"
            },
            "href": "https://api.spotify.com/v1/artists/4FqPRilb0Ja0TKG3RS3y4s",
            "id": "4FqPRilb0Ja0TKG3RS3y4s",
            "name": "Steve Angello",
            "type": "artist",
            "uri": "spotify:artist:4FqPRilb0Ja0TKG3RS3y4s"
        },
        {
            "external_urls": {
                "spotify": "https://open.spotify.com/artist/132Hhe61bhvXtkygENHZHA"
            },
            "href": "https://api.spotify.com/v1/artists/132Hhe61bhvXtkygENHZHA",
            "id": "132Hhe61bhvXtkygENHZHA",
            "name": "Wh0",
            "type": "artist",
            "uri": "spotify:artist:132Hhe61bhvXtkygENHZHA"
        }
    ],
    "copyrights": [
        {
            "text": "\u00a9 2023 Size Records UK Ltd, under exclusive license to UMG Recordings, Inc.",
            "type": "C"
        },
        {
            "text": "\u2117 2023 Size Records UK Ltd, under exclusive license to UMG Recordings, Inc.",
            "type": "P"
        }
    ],
    "external_ids": {
        "upc": "00602458269178"
    },
    "external_urls": {
        "spotify": "https://open.spotify.com/album/36WVqPt4HocsuiPQer82ob"
    },
    "genres": [],
    "href": "https://api.spotify.com/v1/albums/36WVqPt4HocsuiPQer82ob",
    "id": "36WVqPt4HocsuiPQer82ob",
    "images": [
        {
            "height": 640,
            "url": "https://i.scdn.co/image/ab67616d0000b273d1b85127f6d81eb690a68022",
            "width": 640
        },
        {
            "height": 300,
            "url": "https://i.scdn.co/image/ab67616d00001e02d1b85127f6d81eb690a68022",
            "width": 300
        },
        {
            "height": 64,
            "url": "https://i.scdn.co/image/ab67616d00004851d1b85127f6d81eb690a68022",
            "width": 64
        }
    ],
    "is_playable": true,
    "label": "Astralwerks",
    "name": "What You Need",
    "popularity": 46,
    "release_date": "2023-07-21",
    "release_date_precision": "day",
    "total_tracks": 1,
    "tracks": {
        "href": "https://api.spotify.com/v1/albums/36WVqPt4HocsuiPQer82ob/tracks?offset=0&limit=50&market=KR",
        "items": [
            {
                "artists": [
                    {
                        "external_urls": {
                            "spotify": "https://open.spotify.com/artist/4FqPRilb0Ja0TKG3RS3y4s"
                        },
                        "href": "https://api.spotify.com/v1/artists/4FqPRilb0Ja0TKG3RS3y4s",
                        "id": "4FqPRilb0Ja0TKG3RS3y4s",
                        "name": "Steve Angello",
                        "type": "artist",
                        "uri": "spotify:artist:4FqPRilb0Ja0TKG3RS3y4s"
                    },
                    {
                        "external_urls": {
                            "spotify": "https://open.spotify.com/artist/132Hhe61bhvXtkygENHZHA"
                        },
                        "href": "https://api.spotify.com/v1/artists/132Hhe61bhvXtkygENHZHA",
                        "id": "132Hhe61bhvXtkygENHZHA",
                        "name": "Wh0",
                        "type": "artist",
                        "uri": "spotify:artist:132Hhe61bhvXtkygENHZHA"
                    }
                ],
                "disc_number": 1,
                "duration_ms": 218040,
                "explicit": false,
                "external_urls": {
                    "spotify": "https://open.spotify.com/track/2KR32tVW39lfG4tO1yOwdq"
                },
                "href": "https://api.spotify.com/v1/tracks/2KR32tVW39lfG4tO1yOwdq",
                "id": "2KR32tVW39lfG4tO1yOwdq",
                "is_local": false,
                "is_playable": true,
                "name": "What You Need",
                "preview_url": null,
                "track_number": 1,
                "type": "track",
                "uri": "spotify:track:2KR32tVW39lfG4tO1yOwdq"
            }
        ],
        "limit": 50,
        "next": null,
        "offset": 0,
        "previous": null,
        "total": 1
    },
    "type": "album",
    "uri": "spotify:album:36WVqPt4HocsuiPQer82ob"
}{
    "album_type": "single",
    "artists": [
        {
            "external_urls": {
                "spotify": "https://open.spotify.com/artist/4FqPRilb0Ja0TKG3RS3y4s"
            },
            "href": "https://api.spotify.com/v1/artists/4FqPRilb0Ja0TKG3RS3y4s",
            "id": "4FqPRilb0Ja0TKG3RS3y4s",
            "name": "Steve Angello",
            "type": "artist",
            "uri": "spotify:artist:4FqPRilb0Ja0TKG3RS3y4s"
        },
        {
            "external_urls": {
                "spotify": "https://open.spotify.com/artist/132Hhe61bhvXtkygENHZHA"
            },
            "href": "https://api.spotify.com/v1/artists/132Hhe61bhvXtkygENHZHA",
            "id": "132Hhe61bhvXtkygENHZHA",
            "name": "Wh0",
            "type": "artist",
            "uri": "spotify:artist:132Hhe61bhvXtkygENHZHA"
        }
    ],
    "copyrights": [
        {
            "text": "\u00a9 2023 Size Records UK Ltd, under exclusive license to UMG Recordings, Inc.",
            "type": "C"
        },
        {
            "text": "\u2117 2023 Size Records UK Ltd, under exclusive license to UMG Recordings, Inc.",
            "type": "P"
        }
    ],
    "external_ids": {
        "upc": "00602458269178"
    },
    "external_urls": {
        "spotify": "https://open.spotify.com/album/36WVqPt4HocsuiPQer82ob"
    },
    "genres": [],
    "href": "https://api.spotify.com/v1/albums/36WVqPt4HocsuiPQer82ob",
    "id": "36WVqPt4HocsuiPQer82ob",
    "images": [
        {
            "height": 640,
            "url": "https://i.scdn.co/image/ab67616d0000b273d1b85127f6d81eb690a68022",
            "width": 640
        },
        {
            "height": 300,
            "url": "https://i.scdn.co/image/ab67616d00001e02d1b85127f6d81eb690a68022",
            "width": 300
        },
        {
            "height": 64,
            "url": "https://i.scdn.co/image/ab67616d00004851d1b85127f6d81eb690a68022",
            "width": 64
        }
    ],
    "is_playable": true,
    "label": "Astralwerks",
    "name": "What You Need",
    "popularity": 46,
    "release_date": "2023-07-21",
    "release_date_precision": "day",
    "total_tracks": 1,
    "tracks": {
        "href": "https://api.spotify.com/v1/albums/36WVqPt4HocsuiPQer82ob/tracks?offset=0&limit=50&market=KR",
        "items": [
            {
                "artists": [
                    {
                        "external_urls": {
                            "spotify": "https://open.spotify.com/artist/4FqPRilb0Ja0TKG3RS3y4s"
                        },
                        "href": "https://api.spotify.com/v1/artists/4FqPRilb0Ja0TKG3RS3y4s",
                        "id": "4FqPRilb0Ja0TKG3RS3y4s",
                        "name": "Steve Angello",
                        "type": "artist",
                        "uri": "spotify:artist:4FqPRilb0Ja0TKG3RS3y4s"
                    },
                    {
                        "external_urls": {
                            "spotify": "https://open.spotify.com/artist/132Hhe61bhvXtkygENHZHA"
                        },
                        "href": "https://api.spotify.com/v1/artists/132Hhe61bhvXtkygENHZHA",
                        "id": "132Hhe61bhvXtkygENHZHA",
                        "name": "Wh0",
                        "type": "artist",
                        "uri": "spotify:artist:132Hhe61bhvXtkygENHZHA"
                    }
                ],
                "disc_number": 1,
                "duration_ms": 218040,
                "explicit": false,
                "external_urls": {
                    "spotify": "https://open.spotify.com/track/2KR32tVW39lfG4tO1yOwdq"
                },
                "href": "https://api.spotify.com/v1/tracks/2KR32tVW39lfG4tO1yOwdq",
                "id": "2KR32tVW39lfG4tO1yOwdq",
                "is_local": false,
                "is_playable": true,
                "name": "What You Need",
                "preview_url": null,
                "track_number": 1,
                "type": "track",
                "uri": "spotify:track:2KR32tVW39lfG4tO1yOwdq"
            }
        ],
        "limit": 50,
        "next": null,
        "offset": 0,
        "previous": null,
        "total": 1
    },
    "type": "album",
    "uri": "spotify:album:36WVqPt4HocsuiPQer82ob"
}{
    "album_type": "single",
    "artists": [
        {
            "external_urls": {
                "spotify": "https://open.spotify.com/artist/4FqPRilb0Ja0TKG3RS3y4s"
            },
            "href": "https://api.spotify.com/v1/artists/4FqPRilb0Ja0TKG3RS3y4s",
            "id": "4FqPRilb0Ja0TKG3RS3y4s",
            "name": "Steve Angello",
            "type": "artist",
            "uri": "spotify:artist:4FqPRilb0Ja0TKG3RS3y4s"
        },
        {
            "external_urls": {
                "spotify": "https://open.spotify.com/artist/132Hhe61bhvXtkygENHZHA"
            },
            "href": "https://api.spotify.com/v1/artists/132Hhe61bhvXtkygENHZHA",
            "id": "132Hhe61bhvXtkygENHZHA",
            "name": "Wh0",
            "type": "artist",
            "uri": "spotify:artist:132Hhe61bhvXtkygENHZHA"
        }
    ],
    "copyrights": [
        {
            "text": "\u00a9 2023 Size Records UK Ltd, under exclusive license to UMG Recordings, Inc.",
            "type": "C"
        },
        {
            "text": "\u2117 2023 Size Records UK Ltd, under exclusive license to UMG Recordings, Inc.",
            "type": "P"
        }
    ],
    "external_ids": {
        "upc": "00602458269178"
    },
    "external_urls": {
        "spotify": "https://open.spotify.com/album/36WVqPt4HocsuiPQer82ob"
    },
    "genres": [],
    "href": "https://api.spotify.com/v1/albums/36WVqPt4HocsuiPQer82ob",
    "id": "36WVqPt4HocsuiPQer82ob",
    "images": [
        {
            "height": 640,
            "url": "https://i.scdn.co/image/ab67616d0000b273d1b85127f6d81eb690a68022",
            "width": 640
        },
        {
            "height": 300,
            "url": "https://i.scdn.co/image/ab67616d00001e02d1b85127f6d81eb690a68022",
            "width": 300
        },
        {
            "height": 64,
            "url": "https://i.scdn.co/image/ab67616d00004851d1b85127f6d81eb690a68022",
            "width": 64
        }
    ],
    "is_playable": true,
    "label": "Astralwerks",
    "name": "What You Need",
    "popularity": 46,
    "release_date": "2023-07-21",
    "release_date_precision": "day",
    "total_tracks": 1,
    "tracks": {
        "href": "https://api.spotify.com/v1/albums/36WVqPt4HocsuiPQer82ob/tracks?offset=0&limit=50&market=KR",
        "items": [
            {
                "artists": [
                    {
                        "external_urls": {
                            "spotify": "https://open.spotify.com/artist/4FqPRilb0Ja0TKG3RS3y4s"
                        },
                        "href": "https://api.spotify.com/v1/artists/4FqPRilb0Ja0TKG3RS3y4s",
                        "id": "4FqPRilb0Ja0TKG3RS3y4s",
                        "name": "Steve Angello",
                        "type": "artist",
                        "uri": "spotify:artist:4FqPRilb0Ja0TKG3RS3y4s"
                    },
                    {
                        "external_urls": {
                            "spotify": "https://open.spotify.com/artist/132Hhe61bhvXtkygENHZHA"
                        },
                        "href": "https://api.spotify.com/v1/artists/132Hhe61bhvXtkygENHZHA",
                        "id": "132Hhe61bhvXtkygENHZHA",
                        "name": "Wh0",
                        "type": "artist",
                        "uri": "spotify:artist:132Hhe61bhvXtkygENHZHA"
                    }
                ],
                "disc_number": 1,
                "duration_ms": 218040,
                "explicit": false,
                "external_urls": {
                    "spotify": "https://open.spotify.com/track/2KR32tVW39lfG4tO1yOwdq"
                },
                "href": "https://api.spotify.com/v1/tracks/2KR32tVW39lfG4tO1yOwdq",
                "id": "2KR32tVW39lfG4tO1yOwdq",
                "is_local": false,
                "is_playable": true,
                "name": "What You Need",
                "preview_url": null,
                "track_number": 1,
                "type": "track",
                "uri": "spotify:track:2KR32tVW39lfG4tO1yOwdq"
            }
        ],
        "limit": 50,
        "next": null,
        "offset": 0,
        "previous": null,
        "total": 1
    },
    "type": "album",
    "uri": "spotify:album:36WVqPt4HocsuiPQer82ob"
}{
    "album_type": "single",
    "artists": [
        {
            "external_urls": {
                "spotify": "https://open.spotify.com/artist/4FqPRilb0Ja0TKG3RS3y4s"
            },
            "href": "https://api.spotify.com/v1/artists/4FqPRilb0Ja0TKG3RS3y4s",
            "id": "4FqPRilb0Ja0TKG3RS3y4s",
            "name": "Steve Angello",
            "type": "artist",
            "uri": "spotify:artist:4FqPRilb0Ja0TKG3RS3y4s"
        },
        {
            "external_urls": {
                "spotify": "https://open.spotify.com/artist/132Hhe61bhvXtkygENHZHA"
            },
            "href": "https://api.spotify.com/v1/artists/132Hhe61bhvXtkygENHZHA",
            "id": "132Hhe61bhvXtkygENHZHA",
            "name": "Wh0",
            "type": "artist",
            "uri": "spotify:artist:132Hhe61bhvXtkygENHZHA"
        }
    ],
    "copyrights": [
        {
            "text": "\u00a9 2023 Size Records UK Ltd, under exclusive license to UMG Recordings, Inc.",
            "type": "C"
        },
        {
            "text": "\u2117 2023 Size Records UK Ltd, under exclusive license to UMG Recordings, Inc.",
            "type": "P"
        }
    ],
    "external_ids": {
        "upc": "00602458269178"
    },
    "external_urls": {
        "spotify": "https://open.spotify.com/album/36WVqPt4HocsuiPQer82ob"
    },
    "genres": [],
    "href": "https://api.spotify.com/v1/albums/36WVqPt4HocsuiPQer82ob",
    "id": "36WVqPt4HocsuiPQer82ob",
    "images": [
        {
            "height": 640,
            "url": "https://i.scdn.co/image/ab67616d0000b273d1b85127f6d81eb690a68022",
            "width": 640
        },
        {
            "height": 300,
            "url": "https://i.scdn.co/image/ab67616d00001e02d1b85127f6d81eb690a68022",
            "width": 300
        },
        {
            "height": 64,
            "url": "https://i.scdn.co/image/ab67616d00004851d1b85127f6d81eb690a68022",
            "width": 64
        }
    ],
    "is_playable": true,
    "label": "Astralwerks",
    "name": "What You Need",
    "popularity": 46,
    "release_date": "2023-07-21",
    "release_date_precision": "day",
    "total_tracks": 1,
    "tracks": {
        "href": "https://api.spotify.com/v1/albums/36WVqPt4HocsuiPQer82ob/tracks?offset=0&limit=50&market=KR",
        "items": [
            {
                "artists": [
                    {
                        "external_urls": {
                            "spotify": "https://open.spotify.com/artist/4FqPRilb0Ja0TKG3RS3y4s"
                        },
                        "href": "https://api.spotify.com/v1/artists/4FqPRilb0Ja0TKG3RS3y4s",
                        "id": "4FqPRilb0Ja0TKG3RS3y4s",
                        "name": "Steve Angello",
                        "type": "artist",
                        "uri": "spotify:artist:4FqPRilb0Ja0TKG3RS3y4s"
                    },
                    {
                        "external_urls": {
                            "spotify": "https://open.spotify.com/artist/132Hhe61bhvXtkygENHZHA"
                        },
                        "href": "https://api.spotify.com/v1/artists/132Hhe61bhvXtkygENHZHA",
                        "id": "132Hhe61bhvXtkygENHZHA",
                        "name": "Wh0",
                        "type": "artist",
                        "uri": "spotify:artist:132Hhe61bhvXtkygENHZHA"
                    }
                ],
                "disc_number": 1,
                "duration_ms": 218040,
                "explicit": false,
                "external_urls": {
                    "spotify": "https://open.spotify.com/track/2KR32tVW39lfG4tO1yOwdq"
                },
                "href": "https://api.spotify.com/v1/tracks/2KR32tVW39lfG4tO1yOwdq",
                "id": "2KR32tVW39lfG4tO1yOwdq",
                "is_local": false,
                "is_playable": true,
                "name": "What You Need",
                "preview_url": null,
                "track_number": 1,
                "type": "track",
                "uri": "spotify:track:2KR32tVW39lfG4tO1yOwdq"
            }
        ],
        "limit": 50,
        "next": null,
        "offset": 0,
        "previous": null,
        "total": 1
    },
    "type": "album",
    "uri": "spotify:album:36WVqPt4HocsuiPQer82ob"
}{
    "album_type": "single",
    "artists": [
        {
            "external_urls": {
                "spotify": "https://open.spotify.com/artist/4FqPRilb0Ja0TKG3RS3y4s"
            },
            "href": "https://api.spotify.com/v1/artists/4FqPRilb0Ja0TKG3RS3y4s",
            "id": "4FqPRilb0Ja0TKG3RS3y4s",
            "name": "Steve Angello",
            "type": "artist",
            "uri": "spotify:artist:4FqPRilb0Ja0TKG3RS3y4s"
        },
        {
            "external_urls": {
                "spotify": "https://open.spotify.com/artist/132Hhe61bhvXtkygENHZHA"
            },
            "href": "https://api.spotify.com/v1/artists/132Hhe61bhvXtkygENHZHA",
            "id": "132Hhe61bhvXtkygENHZHA",
            "name": "Wh0",
            "type": "artist",
            "uri": "spotify:artist:132Hhe61bhvXtkygENHZHA"
        }
    ],
    "copyrights": [
        {
            "text": "\u00a9 2023 Size Records UK Ltd, under exclusive license to UMG Recordings, Inc.",
            "type": "C"
        },
        {
            "text": "\u2117 2023 Size Records UK Ltd, under exclusive license to UMG Recordings, Inc.",
            "type": "P"
        }
    ],
    "external_ids": {
        "upc": "00602458269178"
    },
    "external_urls": {
        "spotify": "https://open.spotify.com/album/36WVqPt4HocsuiPQer82ob"
    },
    "genres": [],
    "href": "https://api.spotify.com/v1/albums/36WVqPt4HocsuiPQer82ob",
    "id": "36WVqPt4HocsuiPQer82ob",
    "images": [
        {
            "height": 640,
            "url": "https://i.scdn.co/image/ab67616d0000b273d1b85127f6d81eb690a68022",
            "width": 640
        },
        {
            "height": 300,
            "url": "https://i.scdn.co/image/ab67616d00001e02d1b85127f6d81eb690a68022",
            "width": 300
        },
        {
            "height": 64,
            "url": "https://i.scdn.co/image/ab67616d00004851d1b85127f6d81eb690a68022",
            "width": 64
        }
    ],
    "is_playable": true,
    "label": "Astralwerks",
    "name": "What You Need",
    "popularity": 46,
    "release_date": "2023-07-21",
    "release_date_precision": "day",
    "total_tracks": 1,
    "tracks": {
        "href": "https://api.spotify.com/v1/albums/36WVqPt4HocsuiPQer82ob/tracks?offset=0&limit=50&market=KR",
        "items": [
            {
                "artists": [
                    {
                        "external_urls": {
                            "spotify": "https://open.spotify.com/artist/4FqPRilb0Ja0TKG3RS3y4s"
                        },
                        "href": "https://api.spotify.com/v1/artists/4FqPRilb0Ja0TKG3RS3y4s",
                        "id": "4FqPRilb0Ja0TKG3RS3y4s",
                        "name": "Steve Angello",
                        "type": "artist",
                        "uri": "spotify:artist:4FqPRilb0Ja0TKG3RS3y4s"
                    },
                    {
                        "external_urls": {
                            "spotify": "https://open.spotify.com/artist/132Hhe61bhvXtkygENHZHA"
                        },
                        "href": "https://api.spotify.com/v1/artists/132Hhe61bhvXtkygENHZHA",
                        "id": "132Hhe61bhvXtkygENHZHA",
                        "name": "Wh0",
                        "type": "artist",
                        "uri": "spotify:artist:132Hhe61bhvXtkygENHZHA"
                    }
                ],
                "disc_number": 1,
                "duration_ms": 218040,
                "explicit": false,
                "external_urls": {
                    "spotify": "https://open.spotify.com/track/2KR32tVW39lfG4tO1yOwdq"
                },
                "href": "https://api.spotify.com/v1/tracks/2KR32tVW39lfG4tO1yOwdq",
                "id": "2KR32tVW39lfG4tO1yOwdq",
                "is_local": false,
                "is_playable": true,
                "name": "What You Need",
                "preview_url": null,
                "track_number": 1,
                "type": "track",
                "uri": "spotify:track:2KR32tVW39lfG4tO1yOwdq"
            }
        ],
        "limit": 50,
        "next": null,
        "offset": 0,
        "previous": null,
        "total": 1
    },
    "type": "album",
    "uri": "spotify:album:36WVqPt4HocsuiPQer82ob"
}{
    "album_type": "single",
    "artists": [
        {
            "external_urls": {
                "spotify": "https://open.spotify.com/artist/4FqPRilb0Ja0TKG3RS3y4s"
            },
            "href": "https://api.spotify.com/v1/artists/4FqPRilb0Ja0TKG3RS3y4s",
            "id": "4FqPRilb0Ja0TKG3RS3y4s",
            "name": "Steve Angello",
            "type": "artist",
            "uri": "spotify:artist:4FqPRilb0Ja0TKG3RS3y4s"
        },
        {
            "external_urls": {
                "spotify": "https://open.spotify.com/artist/132Hhe61bhvXtkygENHZHA"
            },
            "href": "https://api.spotify.com/v1/artists/132Hhe61bhvXtkygENHZHA",
            "id": "132Hhe61bhvXtkygENHZHA",
            "name": "Wh0",
            "type": "artist",
            "uri": "spotify:artist:132Hhe61bhvXtkygENHZHA"
        }
    ],
    "copyrights": [
        {
            "text": "\u00a9 2023 Size Records UK Ltd, under exclusive license to UMG Recordings, Inc.",
            "type": "C"
        },
        {
            "text": "\u2117 2023 Size Records UK Ltd, under exclusive license to UMG Recordings, Inc.",
            "type": "P"
        }
    ],
    "external_ids": {
        "upc": "00602458269178"
    },
    "external_urls": {
        "spotify": "https://open.spotify.com/album/36WVqPt4HocsuiPQer82ob"
    },
    "genres": [],
    "href": "https://api.spotify.com/v1/albums/36WVqPt4HocsuiPQer82ob",
    "id": "36WVqPt4HocsuiPQer82ob",
    "images": [
        {
            "height": 640,
            "url": "https://i.scdn.co/image/ab67616d0000b273d1b85127f6d81eb690a68022",
            "width": 640
        },
        {
            "height": 300,
            "url": "https://i.scdn.co/image/ab67616d00001e02d1b85127f6d81eb690a68022",
            "width": 300
        },
        {
            "height": 64,
            "url": "https://i.scdn.co/image/ab67616d00004851d1b85127f6d81eb690a68022",
            "width": 64
        }
    ],
    "is_playable": true,
    "label": "Astralwerks",
    "name": "What You Need",
    "popularity": 46,
    "release_date": "2023-07-21",
    "release_date_precision": "day",
    "total_tracks": 1,
    "tracks": {
        "href": "https://api.spotify.com/v1/albums/36WVqPt4HocsuiPQer82ob/tracks?offset=0&limit=50&market=KR",
        "items": [
            {
                "artists": [
                    {
                        "external_urls": {
                            "spotify": "https://open.spotify.com/artist/4FqPRilb0Ja0TKG3RS3y4s"
                        },
                        "href": "https://api.spotify.com/v1/artists/4FqPRilb0Ja0TKG3RS3y4s",
                        "id": "4FqPRilb0Ja0TKG3RS3y4s",
                        "name": "Steve Angello",
                        "type": "artist",
                        "uri": "spotify:artist:4FqPRilb0Ja0TKG3RS3y4s"
                    },
                    {
                        "external_urls": {
                            "spotify": "https://open.spotify.com/artist/132Hhe61bhvXtkygENHZHA"
                        },
                        "href": "https://api.spotify.com/v1/artists/132Hhe61bhvXtkygENHZHA",
                        "id": "132Hhe61bhvXtkygENHZHA",
                        "name": "Wh0",
                        "type": "artist",
                        "uri": "spotify:artist:132Hhe61bhvXtkygENHZHA"
                    }
                ],
                "disc_number": 1,
                "duration_ms": 218040,
                "explicit": false,
                "external_urls": {
                    "spotify": "https://open.spotify.com/track/2KR32tVW39lfG4tO1yOwdq"
                },
                "href": "https://api.spotify.com/v1/tracks/2KR32tVW39lfG4tO1yOwdq",
                "id": "2KR32tVW39lfG4tO1yOwdq",
                "is_local": false,
                "is_playable": true,
                "name": "What You Need",
                "preview_url": null,
                "track_number": 1,
                "type": "track",
                "uri": "spotify:track:2KR32tVW39lfG4tO1yOwdq"
            }
        ],
        "limit": 50,
        "next": null,
        "offset": 0,
        "previous": null,
        "total": 1
    },
    "type": "album",
    "uri": "spotify:album:36WVqPt4HocsuiPQer82ob"
}