{
    "album_type": "single",
    "artists": [
        {
            "external_urls": {
                "spotify": "https://open.spotify.com/artist/6RHTUrRF63xao58xh9FXYJ"
            },
            "href": "https://api.spotify.com/v1/artists/6RHTUrRF63xao58xh9FXYJ",
            "id": "6RHTUrRF63xao58xh9FXYJ",
            "name": "IVE",
            "type": "artist",
            "uri": "spotify:artist:6RHTUrRF63xao58xh9FXYJ"
        }
    ],
    "copyrights": [
        {
            "text": "(C) 2022 Starship Entertainment",
            "type": "C"
        },
        {
            "text": "(P) 2022 Starship Entertainment",
            "type": "P"
        }
    ],
    "external_ids": {
        "upc": "196925429900"
    },
    "external_urls": {
        "spotify": "https://open.spotify.com/album/0nzRF7khA2UDSZa9T0B6Da"
    },
    "genres": [],
    "href": "https://api.spotify.com/v1/albums/0nzRF7khA2UDSZa9T0B6Da",
    "id": "0nzRF7khA2UDSZa9T0B6Da",
    "images": [
        {
            "height": 640,
            "url": "https://i.scdn.co/image/ab67616d0000b27387f53da5fb4ab1171766b2d5",
            "width": 640
        },
        {
            "height": 300,
            "url": "https://i.scdn.co/image/ab67616d00001e0287f53da5fb4ab1171766b2d5",
            "width": 300
        },
        {
            "height": 64,
            "url": "https://i.scdn.co/image/ab67616d0000485187f53da5fb4ab1171766b2d5",
            "width": 64
        }
    ],
    "is_playable": true,
    "label": "Starship Entertainment",
    "name": "After LIKE",
    "popularity": 73,
    "release_date": "2022-08-22",
    "release_date_precision": "day",
    "total_tracks": 2,
    "tracks": {
        "href": "https://api.spotify.com/v1/albums/0nzRF7khA2UDSZa9T0B6Da/tracks?offset=0&limit=50&market=KR",
        "items": [
            {
                "artists": [
                    {
                        "external_urls": {
                            "spotify": "https://open.spotify.com/artist/6RHTUrRF63xao58xh9FXYJ"
                        },
                        "href": "https://api.spotify.com/v1/artists/6RHTUrRF63xao58xh9FXYJ",
                        "id": "6RHTUrRF63xao58xh9FXYJ",
                        "name": "IVE",
                        "type": "artist",
                        "uri": "spotify:artist:6RHTUrRF63xao58xh9FXYJ"
                    }
                ],
                "disc_number": 1,
                "duration_ms": 176973,
                "explicit": false,
                "external_urls": {
                    "spotify": "https://open.spotify.com/track/6CV6j2xz54thzlrWML3kAW"
                },
                "href": "https://api.spotify.com/v1/tracks/6CV6j2xz54thzlrWML3kAW",
                "id": "6CV6j2xz54thzlrWML3kAW",
                "is_local": false,
                "is_playable": true,
                "linked_from": {
                    "external_urls": {
                        "spotify": "https://open.spotify.com/track/2gYj9lubBorOPIVWsTXugG"
                    },
                    "href": "https://api.spotify.com/v1/tracks/2gYj9lubBorOPIVWsTXugG",
                    "id": "2gYj9lubBorOPIVWsTXugG",
                    "type": "track",
                    "uri": "spotify:track:2gYj9lubBorOPIVWsTXugG"
                },
                "name": "After LIKE",
                "preview_url": "https://p.scdn.co/mp3-preview/eaa3bc88f2a9af609aa49294c2ef49000a6d38b3?cid=a18dc6eb0d9042eaa547bad38ee1b237",
                "track_number": 1,
                "type": "track",
                "uri": "spotify:track:6CV6j2xz54thzlrWML3kAW"
            },
            {
                "artists": [
                    {
                        "external_urls": {
                            "spotify": "https://open.spotify.com/artist/6RHTUrRF63xao58xh9FXYJ"
                        },
                        "href": "https://api.spotify.com/v1/artists/6RHTUrRF63xao58xh9FXYJ",
                        "id": "6RHTUrRF63xao58xh9FXYJ",
                        "name": "IVE",
                        "type": "artist",
                        "uri": "spotify:artist:6RHTUrRF63xao58xh9FXYJ"
                    }
                ],
                "disc_number": 1,
                "duration_ms": 193000,
                "explicit": false,
                "external_urls": {
                    "spotify": "https://open.spotify.com/track/2jaZpjWHv68e2FYr0v3WUj"
                },
                "href": "https://api.spotify.com/v1/tracks/2jaZpjWHv68e2FYr0v3WUj",
                "id": "2jaZpjWHv68e2FYr0v3WUj",
                "is_local": false,
                "is_playable": true,
                "linked_from": {
                    "external_urls": {
                        "spotify": "https://open.spotify.com/track/3Owz3vrIE44Hvt0sLsfwHI"
                    },
                    "href": "https://api.spotify.com/v1/tracks/3Owz3vrIE44Hvt0sLsfwHI",
                    "id": "3Owz3vrIE44Hvt0sLsfwHI",
                    "type": "track",
                    "uri": "spotify:track:3Owz3vrIE44Hvt0sLsfwHI"
                },
                "name": "My Satisfaction",
                "preview_url": "https://p.scdn.co/mp3-preview/54cc84677953258b7e7cfdd5d7815eacef5424f5?cid=a18dc6eb0d9042eaa547bad38ee1b237",
                "track_number": 2,
                "type": "track",
                "uri": "spotify:track:2jaZpjWHv68e2FYr0v3WUj"
            }
        ],
        "limit": 50,
        "next": null,
        "offset": 0,
        "previous": null,
        "total": 2
    },
    "type": "album",
    "uri": "spotify:album:0nzRF7khA2UDSZa9T0B6Da"
}{
    "album_type": "single",
    "artists": [
        {
            "external_urls": {
                "spotify": "https://open.spotify.com/artist/6RHTUrRF63xao58xh9FXYJ"
            },
            "href": "https://api.spotify.com/v1/artists/6RHTUrRF63xao58xh9FXYJ",
            "id": "6RHTUrRF63xao58xh9FXYJ",
            "name": "IVE",
            "type": "artist",
            "uri": "spotify:artist:6RHTUrRF63xao58xh9FXYJ"
        }
    ],
    "copyrights": [
        {
            "text": "(C) 2022 Starship Entertainment",
            "type": "C"
        },
        {
            "text": "(P) 2022 Starship Entertainment",
            "type": "P"
        }
    ],
    "external_ids": {
        "upc": "196925429900"
    },
    "external_urls": {
        "spotify": "https://open.spotify.com/album/0nzRF7khA2UDSZa9T0B6Da"
    },
    "genres": [],
    "href": "https://api.spotify.com/v1/albums/0nzRF7khA2UDSZa9T0B6Da",
    "id": "0nzRF7khA2UDSZa9T0B6Da",
    "images": [
        {
            "height": 640,
            "url": "https://i.scdn.co/image/ab67616d0000b27387f53da5fb4ab1171766b2d5",
            "width": 640
        },
        {
            "height": 300,
            "url": "https://i.scdn.co/image/ab67616d00001e0287f53da5fb4ab1171766b2d5",
            "width": 300
        },
        {
            "height": 64,
            "url": "https://i.scdn.co/image/ab67616d0000485187f53da5fb4ab1171766b2d5",
            "width": 64
        }
    ],
    "is_playable": true,
    "label": "Starship Entertainment",
    "name": "After LIKE",
    "popularity": 73,
    "release_date": "2022-08-22",
    "release_date_precision": "day",
    "total_tracks": 2,
    "tracks": {
        "href": "https://api.spotify.com/v1/albums/0nzRF7khA2UDSZa9T0B6Da/tracks?offset=0&limit=50&market=KR",
        "items": [
            {
                "artists": [
                    {
                        "external_urls": {
                            "spotify": "https://open.spotify.com/artist/6RHTUrRF63xao58xh9FXYJ"
                        },
                        "href": "https://api.spotify.com/v1/artists/6RHTUrRF63xao58xh9FXYJ",
                        "id": "6RHTUrRF63xao58xh9FXYJ",
                        "name": "IVE",
                        "type": "artist",
                        "uri": "spotify:artist:6RHTUrRF63xao58xh9FXYJ"
                    }
                ],
                "disc_number": 1,
                "duration_ms": 176973,
                "explicit": false,
                "external_urls": {
                    "spotify": "https://open.spotify.com/track/6CV6j2xz54thzlrWML3kAW"
                },
                "href": "https://api.spotify.com/v1/tracks/6CV6j2xz54thzlrWML3kAW",
                "id": "6CV6j2xz54thzlrWML3kAW",
                "is_local": false,
                "is_playable": true,
                "linked_from": {
                    "external_urls": {
                        "spotify": "https://open.spotify.com/track/2gYj9lubBorOPIVWsTXugG"
                    },
                    "href": "https://api.spotify.com/v1/tracks/2gYj9lubBorOPIVWsTXugG",
                    "id": "2gYj9lubBorOPIVWsTXugG",
                    "type": "track",
                    "uri": "spotify:track:2gYj9lubBorOPIVWsTXugG"
                },
                "name": "After LIKE",
                "preview_url": "https://p.scdn.co/mp3-preview/eaa3bc88f2a9af609aa49294c2ef49000a6d38b3?cid=a18dc6eb0d9042eaa547bad38ee1b237",
                "track_number": 1,
                "type": "track",
                "uri": "spotify:track:6CV6j2xz54thzlrWML3kAW"
            },
            {
                "artists": [
                    {
                        "external_urls": {
                            "spotify": "https://open.spotify.com/artist/6RHTUrRF63xao58xh9FXYJ"
                        },
                        "href": "https://api.spotify.com/v1/artists/6RHTUrRF63xao58xh9FXYJ",
                        "id": "6RHTUrRF63xao58xh9FXYJ",
                        "name": "IVE",
                        "type": "artist",
                        "uri": "spotify:artist:6RHTUrRF63xao58xh9FXYJ"
                    }
                ],
                "disc_number": 1,
                "duration_ms": 193000,
                "explicit": false,
                "external_urls": {
                    "spotify": "https://open.spotify.com/track/2jaZpjWHv68e2FYr0v3WUj"
                },
                "href": "https://api.spotify.com/v1/tracks/2jaZpjWHv68e2FYr0v3WUj",
                "id": "2jaZpjWHv68e2FYr0v3WUj",
                "is_local": false,
                "is_playable": true,
                "linked_from": {
                    "external_urls": {
                        "spotify": "https://open.spotify.com/track/3Owz3vrIE44Hvt0sLsfwHI"
                    },
                    "href": "https://api.spotify.com/v1/tracks/3Owz3vrIE44Hvt0sLsfwHI",
                    "id": "3Owz3vrIE44Hvt0sLsfwHI",
                    "type": "track",
                    "uri": "spotify:track:3Owz3vrIE44Hvt0sLsfwHI"
                },
                "name": "My Satisfaction",
                "preview_url": "https://p.scdn.co/mp3-preview/54cc84677953258b7e7cfdd5d7815eacef5424f5?cid=a18dc6eb0d9042eaa547bad38ee1b237",
                "track_number": 2,
                "type": "track",
                "uri": "spotify:track:2jaZpjWHv68e2FYr0v3WUj"
            }
        ],
        "limit": 50,
        "next": null,
        "offset": 0,
        "previous": null,
        "total": 2
    },
    "type": "album",
    "uri": "spotify:album:0nzRF7khA2UDSZa9T0B6Da"
}{
    "album_type": "single",
    "artists": [
        {
            "external_urls": {
                "spotify": "https://open.spotify.com/artist/6RHTUrRF63xao58xh9FXYJ"
            },
            "href": "https://api.spotify.com/v1/artists/6RHTUrRF63xao58xh9FXYJ",
            "id": "6RHTUrRF63xao58xh9FXYJ",
            "name": "IVE",
            "type": "artist",
            "uri": "spotify:artist:6RHTUrRF63xao58xh9FXYJ"
        }
    ],
    "copyrights": [
        {
            "text": "(C) 2022 Starship Entertainment",
            "type": "C"
        },
        {
            "text": "(P) 2022 Starship Entertainment",
            "type": "P"
        }
    ],
    "external_ids": {
        "upc": "196925429900"
    },
    "external_urls": {
        "spotify": "https://open.spotify.com/album/0nzRF7khA2UDSZa9T0B6Da"
    },
    "genres": [],
    "href": "https://api.spotify.com/v1/albums/0nzRF7khA2UDSZa9T0B6Da",
    "id": "0nzRF7khA2UDSZa9T0B6Da",
    "images": [
        {
            "height": 640,
            "url": "https://i.scdn.co/image/ab67616d0000b27387f53da5fb4ab1171766b2d5",
            "width": 640
        },
        {
            "height": 300,
            "url": "https://i.scdn.co/image/ab67616d00001e0287f53da5fb4ab1171766b2d5",
            "width": 300
        },
        {
            "height": 64,
            "url": "https://i.scdn.co/image/ab67616d0000485187f53da5fb4ab1171766b2d5",
            "width": 64
        }
    ],
    "is_playable": true,
    "label": "Starship Entertainment",
    "name": "After LIKE",
    "popularity": 73,
    "release_date": "2022-08-22",
    "release_date_precision": "day",
    "total_tracks": 2,
    "tracks": {
        "href": "https://api.spotify.com/v1/albums/0nzRF7khA2UDSZa9T0B6Da/tracks?offset=0&limit=50&market=KR",
        "items": [
            {
                "artists": [
                    {
                        "external_urls": {
                            "spotify": "https://open.spotify.com/artist/6RHTUrRF63xao58xh9FXYJ"
                        },
                        "href": "https://api.spotify.com/v1/artists/6RHTUrRF63xao58xh9FXYJ",
                        "id": "6RHTUrRF63xao58xh9FXYJ",
                        "name": "IVE",
                        "type": "artist",
                        "uri": "spotify:artist:6RHTUrRF63xao58xh9FXYJ"
                    }
                ],
                "disc_number": 1,
                "duration_ms": 176973,
                "explicit": false,
                "external_urls": {
                    "spotify": "https://open.spotify.com/track/6CV6j2xz54thzlrWML3kAW"
                },
                "href": "https://api.spotify.com/v1/tracks/6CV6j2xz54thzlrWML3kAW",
                "id": "6CV6j2xz54thzlrWML3kAW",
                "is_local": false,
                "is_playable": true,
                "linked_from": {
                    "external_urls": {
                        "spotify": "https://open.spotify.com/track/2gYj9lubBorOPIVWsTXugG"
                    },
                    "href": "https://api.spotify.com/v1/tracks/2gYj9lubBorOPIVWsTXugG",
                    "id": "2gYj9lubBorOPIVWsTXugG",
                    "type": "track",
                    "uri": "spotify:track:2gYj9lubBorOPIVWsTXugG"
                },
                "name": "After LIKE",
                "preview_url": "https://p.scdn.co/mp3-preview/eaa3bc88f2a9af609aa49294c2ef49000a6d38b3?cid=18f16e31aa1449669e888d1f09644ca2",
                "track_number": 1,
                "type": "track",
                "uri": "spotify:track:6CV6j2xz54thzlrWML3kAW"
            },
            {
                "artists": [
                    {
                        "external_urls": {
                            "spotify": "https://open.spotify.com/artist/6RHTUrRF63xao58xh9FXYJ"
                        },
                        "href": "https://api.spotify.com/v1/artists/6RHTUrRF63xao58xh9FXYJ",
                        "id": "6RHTUrRF63xao58xh9FXYJ",
                        "name": "IVE",
                        "type": "artist",
                        "uri": "spotify:artist:6RHTUrRF63xao58xh9FXYJ"
                    }
                ],
                "disc_number": 1,
                "duration_ms": 193000,
                "explicit": false,
                "external_urls": {
                    "spotify": "https://open.spotify.com/track/2jaZpjWHv68e2FYr0v3WUj"
                },
                "href": "https://api.spotify.com/v1/tracks/2jaZpjWHv68e2FYr0v3WUj",
                "id": "2jaZpjWHv68e2FYr0v3WUj",
                "is_local": false,
                "is_playable": true,
                "linked_from": {
                    "external_urls": {
                        "spotify": "https://open.spotify.com/track/3Owz3vrIE44Hvt0sLsfwHI"
                    },
                    "href": "https://api.spotify.com/v1/tracks/3Owz3vrIE44Hvt0sLsfwHI",
                    "id": "3Owz3vrIE44Hvt0sLsfwHI",
                    "type": "track",
                    "uri": "spotify:track:3Owz3vrIE44Hvt0sLsfwHI"
                },
                "name": "My Satisfaction",
                "preview_url": "https://p.scdn.co/mp3-preview/54cc84677953258b7e7cfdd5d7815eacef5424f5?cid=18f16e31aa1449669e888d1f09644ca2",
                "track_number": 2,
                "type": "track",
                "uri": "spotify:track:2jaZpjWHv68e2FYr0v3WUj"
            }
        ],
        "limit": 50,
        "next": null,
        "offset": 0,
        "previous": null,
        "total": 2
    },
    "type": "album",
    "uri": "spotify:album:0nzRF7khA2UDSZa9T0B6Da"
}